<?xml version="1.0" encoding="UTF-8"?>
<files psalm-version="4.30.0@d0bc6e25d89f649e4f36a534f330f8bb4643dd69">
  <file src="src/MappingListSerializer.php">
    <MixedArgumentTypeCoercion occurrences="1">
      <code>$array</code>
    </MixedArgumentTypeCoercion>
    <MixedAssignment occurrences="1">
      <code>$array</code>
    </MixedAssignment>
  </file>
  <file src="src/WikibaseRdfExtension.php">
    <MixedArgumentTypeCoercion occurrences="1">
      <code>(array)$services-&gt;getMainConfig()-&gt;get( 'AvailableRights' )</code>
    </MixedArgumentTypeCoercion>
    <MixedArrayAccess occurrences="1">
      <code>WikibaseRepo::getSettings()-&gt;getSetting( 'string-limits' )['PT:url']</code>
    </MixedArrayAccess>
    <PossiblyFalseArgument occurrences="1">
      <code>MediaWikiServices::getInstance()-&gt;getDBLoadBalancer()-&gt;getConnection( ILoadBalancer::DB_REPLICA )</code>
    </PossiblyFalseArgument>
  </file>
</files>
